tddmon/__init__.py
tddmon/__main__.py
tddmon/tests/test_acceptance.py
tddmon/tests/test_unit.py
tddmon/tests/__init__.py
tddmon-0.2.0.dist-info/top_level.txt
tddmon-0.2.0.dist-info/METADATA
tddmon-0.2.0.dist-info/entry_points.txt
tddmon-0.2.0.dist-info/DESCRIPTION.rst
tddmon-0.2.0.dist-info/metadata.json
tddmon-0.2.0.dist-info/WHEEL
tddmon-0.2.0.dist-info/RECORD
