Metadata-Version: 2.0
Name: tddmon
Version: 0.2.0
Summary: TDD flow monitor.
Home-page: http://kidosoft.pl
Author: Jakub STOLARSKI (Dryobates)
Author-email: jakub.stolarski@kidosoft.pl
License: beerware
Keywords: tdd,testing
Platform: UNKNOWN
Classifier: Development Status :: 4 - Beta
Classifier: Environment :: Web Environment
Classifier: Intended Audience :: Developers
Classifier: License :: OSI Approved :: BSD License
Classifier: Operating System :: OS Independent
Classifier: Framework :: Django
Classifier: Programming Language :: Python
Classifier: Topic :: Utilities
